fstool/__init__.py
fstool/__main__.py
fstool/_config.py
fstool/_crawler.py
fstool/_main.py
fstool/_structure.py
fstool/external/__init__.py
fstool/external/regexfind.py
fstool-0.1.8.dist-info/LICENSE
fstool-0.1.8.dist-info/METADATA
fstool-0.1.8.dist-info/WHEEL
fstool-0.1.8.dist-info/top_level.txt
fstool-0.1.8.dist-info/RECORD
