Metadata-Version: 2.1
Name: fstool
Version: 0.1.8
Summary: file system tool extension
Home-page: https://github.com/mHaisham/fstool
Author: mhaisham
Author-email: mhaisham79@gmail.com
License: UNKNOWN
Platform: UNKNOWN
Requires-Python: >=3.6
